[{"id":1,"name":"Richie Dunrige","email":"rdunrige0@sfgate.com","phoneNumber":"+48 122 516 6079","pack":1,"status":2,"rating":3.7},
{"id":2,"name":"Montgomery Dimelow","email":"mdimelow1@umn.edu","phoneNumber":"+62 740 101 3170","pack":5,"status":2,"rating":1.5},
{"id":3,"name":"Faber Blackmore","email":"fblackmore2@census.gov","phoneNumber":"+86 609 706 6963","pack":6,"status":2,"rating":4.7},
{"id":4,"name":"Piggy Waple","email":"pwaple3@a8.net","phoneNumber":"+81 244 587 5960","pack":5,"status":3,"rating":1.4},
{"id":5,"name":"Tami Keningham","email":"tkeningham4@soup.io","phoneNumber":"+251 788 617 7416","pack":6,"status":3,"rating":4.4},
{"id":6,"name":"Rriocard Anscombe","email":"ranscombe5@google.com.hk","phoneNumber":"+86 571 758 9652","pack":1,"status":3,"rating":2.2},
{"id":7,"name":"Nelly Buckam","email":"nbuckam6@goo.ne.jp","phoneNumber":"+353 591 816 8320","pack":5,"status":1,"rating":3.4},
{"id":8,"name":"Lenci de Nore","email":"lde7@scribd.com","phoneNumber":"+7 858 556 0153","pack":5,"status":2,"rating":4.6},
{"id":9,"name":"Morgan Mixworthy","email":"mmixworthy8@craigslist.org","phoneNumber":"+44 970 807 7239","pack":1,"status":3,"rating":4.3},
{"id":10,"name":"Nolly Behne","email":"nbehne9@hostgator.com","phoneNumber":"+86 185 603 5573","pack":5,"status":1,"rating":3.6},
{"id":11,"name":"Buffy Frick","email":"bfricka@blogtalkradio.com","phoneNumber":"+231 158 316 3800","pack":8,"status":2,"rating":2.6},
{"id":12,"name":"Alix Assel","email":"aasselb@skype.com","phoneNumber":"+86 528 619 0322","pack":1,"status":2,"rating":2.6},
{"id":13,"name":"Sollie McGarry","email":"smcgarryc@domainmarket.com","phoneNumber":"+84 348 418 0350","pack":1,"status":3,"rating":4.0},
{"id":14,"name":"Bradley Cloy","email":"bcloyd@moonfruit.com","phoneNumber":"+86 309 112 2111","pack":8,"status":3,"rating":2.1},
{"id":15,"name":"Giraldo Jacobsson","email":"gjacobssone@businessweek.com","phoneNumber":"+7 320 343 6374","pack":8,"status":3,"rating":1.7},
{"id":16,"name":"Nonna Harral","email":"nharralf@thetimes.co.uk","phoneNumber":"+234 839 366 8153","pack":3,"status":2,"rating":4.5},
{"id":17,"name":"Alissa Bendelow","email":"abendelowg@nationalgeographic.com","phoneNumber":"+86 339 479 7932","pack":5,"status":3,"rating":1.7},
{"id":18,"name":"Enrique Hush","email":"ehushh@howstuffworks.com","phoneNumber":"+7 787 399 4721","pack":5,"status":2,"rating":1.9},
{"id":19,"name":"Stacee Keston","email":"skestoni@gov.uk","phoneNumber":"+86 913 952 4513","pack":6,"status":1,"rating":3.1},
{"id":20,"name":"Missy Sowersby","email":"msowersbyj@woothemes.com","phoneNumber":"+51 925 516 8659","pack":6,"status":2,"rating":3.7},
{"id":21,"name":"Liana Spadollini","email":"lspadollinik@wsj.com","phoneNumber":"+54 629 786 1721","pack":8,"status":3,"rating":2.6},
{"id":22,"name":"Murdock Batha","email":"mbathal@constantcontact.com","phoneNumber":"+63 489 328 0233","pack":8,"status":1,"rating":2.9},
{"id":23,"name":"Marlyn Delue","email":"mdeluem@mayoclinic.com","phoneNumber":"+1 821 301 8089","pack":8,"status":3,"rating":2.7},
{"id":24,"name":"Erena Olivera","email":"eoliveran@statcounter.com","phoneNumber":"+53 728 643 9756","pack":1,"status":1,"rating":1.8},
{"id":25,"name":"Burr Dallywater","email":"bdallywatero@jimdo.com","phoneNumber":"+62 326 358 8048","pack":6,"status":1,"rating":3.5},
{"id":26,"name":"Frants Varnals","email":"fvarnalsp@slate.com","phoneNumber":"+86 142 466 5258","pack":2,"status":2,"rating":1.4},
{"id":27,"name":"Meier Whelpdale","email":"mwhelpdaleq@reddit.com","phoneNumber":"+86 416 741 0160","pack":2,"status":1,"rating":3.5},
{"id":28,"name":"Duke Sherrin","email":"dsherrinr@go.com","phoneNumber":"+33 496 117 2828","pack":6,"status":3,"rating":3.5},
{"id":29,"name":"Berget Dawtre","email":"bdawtres@discovery.com","phoneNumber":"+387 464 410 8948","pack":8,"status":1,"rating":2.5},
{"id":30,"name":"Paulette Gagan","email":"pgagant@irs.gov","phoneNumber":"+46 324 757 7064","pack":1,"status":2,"rating":2.6}]